CHANGES.rst
MANIFEST.in
README.rst
setup.cfg
setup.py
clue_sqlaloader/__init__.py
clue_sqlaloader/tests.py
clue_sqlaloader/tests_flymake.py
clue_sqlaloader.egg-info/PKG-INFO
clue_sqlaloader.egg-info/SOURCES.txt
clue_sqlaloader.egg-info/dependency_links.txt
clue_sqlaloader.egg-info/not-zip-safe
clue_sqlaloader.egg-info/requires.txt
clue_sqlaloader.egg-info/top_level.txt