Metadata-Version: 1.0
Name: clue-sqlaloader
Version: 0.1.1
Summary: Data loader for SQLAlchemy
Home-page: https://github.com/clueproject/clue_sqlaloader
Author: Rocky Burt
Author-email: rocky@serverzen.com
License: BSD
Keywords: sqlalchemy clue yaml sql
Platform: UNKNOWN
Classifier: License :: OSI Approved :: BSD License
